gakp_pyfunk-0.4.1.dist-info/DESCRIPTION.rst
gakp_pyfunk-0.4.1.dist-info/LICENSE.txt
gakp_pyfunk-0.4.1.dist-info/METADATA
gakp_pyfunk-0.4.1.dist-info/RECORD
gakp_pyfunk-0.4.1.dist-info/WHEEL
gakp_pyfunk-0.4.1.dist-info/metadata.json
gakp_pyfunk-0.4.1.dist-info/top_level.txt
pyfunk/__init__.py
pyfunk/collections.py
pyfunk/combinators.py
pyfunk/misc.py
pyfunk/monads/__init__.py
pyfunk/monads/base.py
pyfunk/monads/const.py
pyfunk/monads/either.py
pyfunk/monads/identity.py
pyfunk/monads/io.py
pyfunk/monads/maybe.py
pyfunk/monads/reader.py
pyfunk/monads/state.py
pyfunk/monads/task.py
pyfunk/monads/writer.py
