Metadata-Version: 2.0
Name: gakp-pyfunk
Version: 0.4.1
Summary: UNKNOWN
Home-page: https://gitlab.com/danceasarxx/gakp-pyfunc.git
Author: Arewa Olakunle
Author-email: arewa.olakunle@gmail.com
License: UNKNOWN
Platform: any
